mlprepare/__init__.py
mlprepare/prep_funcs.py
mlprep_ls-0.3.0.dist-info/LICENSE
mlprep_ls-0.3.0.dist-info/METADATA
mlprep_ls-0.3.0.dist-info/WHEEL
mlprep_ls-0.3.0.dist-info/top_level.txt
mlprep_ls-0.3.0.dist-info/RECORD
