Metadata-Version: 2.1
Name: mlprep-ls
Version: 0.3.0
Summary: Small package for preprocessing data.
Home-page: https://github.com/lschmiddey/ml_preproc
Author: Lasse Schmidt
Author-email: lasse.schmidt@live.de
License: UNKNOWN
Platform: UNKNOWN
Classifier: Programming Language :: Python :: 3
Classifier: License :: OSI Approved :: MIT License
Classifier: Operating System :: OS Independent
Requires-Python: >=3.6
